{"menus":[{"id":"MenuPrincipale","name":"Menu Principale","description":"Menu Principale","products":[{"id":"Cola"},{"id":"Panino"},{"id":"a"}]},{"id":"MenuFestaPatronale","name":"Menu Festa Patronale","description":"Menu festa","products":[{"id":"Cola"},{"id":"Panino"},{"id":"a"}]}],"productsCategories":[{"id":"drinks","name":"Drinks","description":"Bevande"},{"id":"food","name":"Food","description":"Cibi"},{"id":"a","name":"a","description":""},{"id":"b","name":"b","description":""}],"products":[{"id":"Cola","name":"Cola","category":"drinks","price":1.5,"photo":"photo.jpg","description":"Refreshing cola drink","active":true,"ingredients":["Water","Sugar","Carbon Dioxide"]},{"id":"Panino","name":"Panino","category":"food","price":2.5,"photo":"photo.jpg","description":"Delicious sandwich","active":true,"ingredients":["Bread","Ham","Cheese","Lettuce"]},{"id":"a","name":"a","category":"a","price":23,"description":"","photo":"","ingredients":[""]}],"activeMenu":"MenuFestaPatronale","location":{"latitude":39.8888991,"longitude":18.3696157}}